[
  {
    "id": 1,
    "auction_house_name": "Aucor Auctioneers",
    "legal_name": "Aucor Auctioneers (Pty) Ltd",
    "website_url": "https://www.aucor.com",
    "address": "19 Nelson Mandela Drive",
    "city": "Centurion",
    "province": "Gauteng",
    "contact_email": "info@aucor.com",
    "contact_phone": "+27 12 677 8060",
    "years_operating": "50+",
    "company_type": "Pty Ltd",
    "https_secure": "Yes",
    "registration_number": "",
    "vat_registered": "Yes",
    "estate_license": "Yes",
    "popia_policy": "Yes",
    "terms_page": "Yes",
    "refund_policy": "Yes",
    "licensing_claims": "Yes",
    "auction_types": ["Vehicle", "Property", "Industrial", "Machinery", "Liquidation"],
    "auction_format": "Hybrid",
    "auction_platform": "Proprietary Online Platform",
    "categories_auctioned": ["Property", "Vehicles", "Industrial Assets"],
    "auction_frequency": "Weekly",
    "collection_locations": ["Centurion", "Johannesburg", "Cape Town"],
    "provincial_reach": ["Gauteng", "Western Cape", "KwaZulu-Natal"],
    "national_or_regional": "National",
    "best_for_tags": ["Dealers", "Property Investors", "Industrial Buyers"],
    "operational_metrics": {
      "avg_transfer_days": "7-14",
      "avg_refund_time": "3-5",
      "settlement_flexibility": "Yes",
      "deposit_percent": null,
      "deposit_amount": "R5,000-R10,000",
      "buyer_premium_percent": "10-15%",
      "admin_fees": "Variable",
      "vat_on_premium": "Yes",
      "storage_penalties": "Yes",
      "hidden_fees": "No",
      "payment_window_days": "2-3",
      "inspection_offered": "Yes",
      "clearance_rate": "Moderate",
      "discount_competitiveness": "Moderate"
    },
    "reputation_signals": {
      "google_rating": 3.9,
      "google_review_count": 450,
      "trustpilot_rating": null,
      "trustpilot_review_count": null,
      "media_mentions_count": null,
      "media_mentions_sample": [],
      "domain_age_years": 20,
      "social_media_followers": ["Facebook 20k", "LinkedIn 5k"]
    },
    "complaints_incidents": {
      "deposit_refund": "Yes",
      "transfer_delay": "Yes",
      "misrepresentation": null,
      "dispute_ratio": null,
      "right_of_reply": "Yes"
    },
    "intelligence_fields": {
      "trust_score": null,
      "risk_score": null,
      "fee_transparency_score": null,
      "institutional_grade": null,
      "complaint_rate": null,
      "verification_level": "Unverified"
    }
  },
  {
    "id": 2,
    "auction_house_name": "Bidders Choice",
    "legal_name": "Bidders Choice Auctioneers CC",
    "website_url": "https://www.bidderschoice.co.za",
    "address": "478 James Street",
    "city": "Midrand",
    "province": "Gauteng",
    "contact_email": "info@bidderschoice.co.za",
    "contact_phone": "+27 12 940 8683",
    "years_operating": "20+",
    "company_type": "CC",
    "https_secure": "Yes",
    "registration_number": "",
    "vat_registered": "Yes",
    "estate_license": "Yes",
    "popia_policy": "Yes",
    "terms_page": "Yes",
    "refund_policy": "Yes",
    "licensing_claims": "Yes",
    "auction_types": ["Property", "Industrial", "Machinery", "Liquidation"],
    "auction_format": "Hybrid",
    "auction_platform": "Proprietary Online Platform",
    "categories_auctioned": ["Property", "Vehicles", "Industrial Assets"],
    "auction_frequency": "Weekly",
    "collection_locations": ["Midrand"],
    "provincial_reach": ["Gauteng"],
    "national_or_regional": "Regional",
    "best_for_tags": ["Dealers", "Property Investors"],
    "operational_metrics": {
      "avg_transfer_days": "7-10",
      "avg_refund_time": "3-5",
      "settlement_flexibility": "Yes",
      "deposit_percent": null,
      "deposit_amount": "R5,000",
      "buyer_premium_percent": "10%",
      "admin_fees": "Variable",
      "vat_on_premium": "Yes",
      "storage_penalties": "Yes",
      "hidden_fees": "No",
      "payment_window_days": "2",
      "inspection_offered": "Yes",
      "clearance_rate": "Moderate",
      "discount_competitiveness": "Moderate"
    },
    "reputation_signals": {
      "google_rating": 4.2,
      "google_review_count": 120,
      "trustpilot_rating": null,
      "trustpilot_review_count": null,
      "media_mentions_count": null,
      "media_mentions_sample": [],
      "domain_age_years": 15,
      "social_media_followers": ["Facebook 10k", "LinkedIn 3k"]
    },
    "complaints_incidents": {
      "deposit_refund": null,
      "transfer_delay": "Yes",
      "misrepresentation": "Yes",
      "dispute_ratio": null,
      "right_of_reply": "Yes"
    },
    "intelligence_fields": {
      "trust_score": null,
      "risk_score": null,
      "fee_transparency_score": null,
      "institutional_grade": null,
      "complaint_rate": null,
      "verification_level": "Unverified"
    }
  },
  {
    "id": 3,
    "auction_house_name": "High Street Auctions",
    "legal_name": "High Street Auction Co. (Pty) Ltd",
    "website_url": "https://www.highstreetauctions.com",
    "address": "63 Bryanston Drive",
    "city": "Bryanston",
    "province": "Gauteng",
    "contact_email": "info@highstreetauctions.com",
    "contact_phone": "+27 11 446 8800",
    "years_operating": "15+",
    "company_type": "Pty Ltd",
    "https_secure": "Yes",
    "registration_number": "",
    "vat_registered": "Yes",
    "estate_license": "Yes",
    "popia_policy": "Yes",
    "terms_page": "Yes",
    "refund_policy": "Yes",
    "licensing_claims": "Yes",
    "auction_types": ["Property"],
    "auction_format": "Hybrid",
    "auction_platform": "Proprietary Online Platform",
    "categories_auctioned": ["Commercial Property", "Residential Property"],
    "auction_frequency": "Monthly",
    "collection_locations": ["Bryanston"],
    "provincial_reach": ["Gauteng"],
    "national_or_regional": "National",
    "best_for_tags": ["Property Investors"],
    "operational_metrics": {
      "avg_transfer_days": "14-21",
      "avg_refund_time": "3-5",
      "settlement_flexibility": "Yes",
      "deposit_percent": "10% of purchase price",
      "deposit_amount": null,
      "buyer_premium_percent": "10-12%",
      "admin_fees": "Variable",
      "vat_on_premium": "Yes",
      "storage_penalties": "Yes",
      "hidden_fees": "No",
      "payment_window_days": "7",
      "inspection_offered": "Yes",
      "clearance_rate": "High",
      "discount_competitiveness": "Moderate"
    },
    "reputation_signals": {
      "google_rating": 4.5,
      "google_review_count": 200,
      "trustpilot_rating": null,
      "trustpilot_review_count": null,
      "media_mentions_count": null,
      "media_mentions_sample": [],
      "domain_age_years": 12,
      "social_media_followers": ["Facebook 15k", "LinkedIn 7k"]
    },
    "complaints_incidents": {
      "deposit_refund": null,
      "transfer_delay": "Yes",
      "misrepresentation": null,
      "dispute_ratio": null,
      "right_of_reply": "Yes"
    },
    "intelligence_fields": {
      "trust_score": null,
      "risk_score": null,
      "fee_transparency_score": null,
      "institutional_grade": null,
      "complaint_rate": null,
      "verification_level": "Unverified"
    }
  },
  {
    "id": 4,
    "auction_house_name": "Prime Auctions",
    "legal_name": "Prime Auctions (Pty) Ltd",
    "website_url": "https://www.primeauctions.co.za",
    "address": "Durbanville Business Park",
    "city": "Durbanville",
    "province": "Western Cape",
    "contact_email": "info@primeauctions.co.za",
    "contact_phone": "+27 21 975 7222",
    "years_operating": "15+",
    "company_type": "Pty Ltd",
    "https_secure": "Yes",
    "registration_number": "",
    "vat_registered": "Yes",
    "estate_license": "Yes",
    "popia_policy": "Yes",
    "terms_page": "Yes",
    "refund_policy": "Yes",
    "licensing_claims": "Yes",
    "auction_types": ["Property", "Industrial", "Machinery"],
    "auction_format": "Hybrid",
    "auction_platform": "Proprietary Online Platform",
    "categories_auctioned": ["Property", "Industrial Assets"],
    "auction_frequency": "Monthly",
    "collection_locations": ["Durbanville"],
    "provincial_reach": ["Western Cape"],
    "national_or_regional": "Regional",
    "best_for_tags": ["Property Investors", "Industrial Buyers"],
    "operational_metrics": {
      "avg_transfer_days": "14",
      "avg_refund_time": "3-5",
      "settlement_flexibility": "Yes",
      "deposit_percent": "10% of purchase price",
      "deposit_amount": null,
      "buyer_premium_percent": "10%",
      "admin_fees": "Variable",
      "vat_on_premium": "Yes",
      "storage_penalties": "Yes",
      "hidden_fees": "No",
      "payment_window_days": "7",
      "inspection_offered": "Yes",
      "clearance_rate": "Moderate",
      "discount_competitiveness": "Moderate"
    },
    "reputation_signals": {
      "google_rating": 4.4,
      "google_review_count": 10,
      "trustpilot_rating": null,
      "trustpilot_review_count": null,
      "media_mentions_count": null,
      "media_mentions_sample": [],
      "domain_age_years": 10,
      "social_media_followers": ["Facebook 3k"]
    },
    "complaints_incidents": {
      "deposit_refund": null,
      "transfer_delay": null,
      "misrepresentation": "Yes",
      "dispute_ratio": null,
      "right_of_reply": "Yes"
    },
    "intelligence_fields": {
      "trust_score": null,
      "risk_score": null,
      "fee_transparency_score": null,
      "institutional_grade": null,
      "complaint_rate": null,
      "verification_level": "Unverified"
    }
  },
  {
    "id": 5,
    "auction_house_name": "Auction Nation",
    "legal_name": "Auction Nation (Pty) Ltd",
    "website_url": "https://www.auctionnation.co.za",
    "address": "Unit 5, 1st Floor, Northlands Corner",
    "city": "North Riding",
    "province": "Gauteng",
    "contact_email": "info@auctionnation.co.za",
    "contact_phone": "+27 10 100 3099",
    "years_operating": "10+",
    "company_type": "Pty Ltd",
    "https_secure": "Yes",
    "registration_number": "",
    "vat_registered": "Yes",
    "estate_license": "Yes",
    "popia_policy": "Yes",
    "terms_page": "Yes",
    "refund_policy": "Yes",
    "licensing_claims": "Yes",
    "auction_types": ["Vehicle", "Property", "Industrial", "Salvage"],
    "auction_format": "Online",
    "auction_platform": "Proprietary Online Platform",
    "categories_auctioned": ["Property", "Vehicles", "Salvage Assets"],
    "auction_frequency": "Weekly",
    "collection_locations": ["Johannesburg"],
    "provincial_reach": ["Gauteng"],
    "national_or_regional": "Regional",
    "best_for_tags": ["Dealers", "Salvage Flippers"],
    "operational_metrics": {
      "avg_transfer_days": "7-10",
      "avg_refund_time": "3-5",
      "settlement_flexibility": "Yes",
      "deposit_percent": null,
      "deposit_amount": "R5,000-R10,000",
      "buyer_premium_percent": "10-15%",
      "admin_fees": "Variable",
      "vat_on_premium": "Yes",
      "storage_penalties": "Yes",
      "hidden_fees": "No",
      "payment_window_days": "2",
      "inspection_offered": "Yes",
      "clearance_rate": "Moderate",
      "discount_competitiveness": "Moderate"
    },
    "reputation_signals": {
      "google_rating": 1,
      "google_review_count": 26,
      "trustpilot_rating": null,
      "trustpilot_review_count": null,
      "media_mentions_count": null,
      "media_mentions_sample": [],
      "domain_age_years": 8,
      "social_media_followers": ["Facebook 5k", "LinkedIn 2k"]
    },
    "complaints_incidents": {
      "deposit_refund": "Yes",
      "transfer_delay": null,
      "misrepresentation": "Yes",
      "dispute_ratio": null,
      "right_of_reply": "Yes"
    },
    "intelligence_fields": {
      "trust_score": null,
      "risk_score": null,
      "fee_transparency_score": null,
      "institutional_grade": null,
      "complaint_rate": null,
      "verification_level": "Unverified"
    }
  },
  {
    "id": 6,
    "auction_house_name": "SA Auction Group",
    "legal_name": "SA Auction Group (Pty) Ltd",
    "website_url": "https://www.saauctiongroup.co.za",
    "address": "Plot 59, Rietfontein",
    "city": "Pretoria",
    "province": "Gauteng",
    "contact_email": "info@saauctiongroup.co.za",
    "contact_phone": "+27 12 940 8683",
    "years_operating": "10+",
    "company_type": "Pty Ltd",
    "https_secure": "Yes",
    "registration_number": "",
    "vat_registered": "Yes",
    "estate_license": "Yes",
    "popia_policy": "Yes",
    "terms_page": "Yes",
    "refund_policy": "Yes",
    "licensing_claims": "Yes",
    "auction_types": ["Vehicle", "Property", "Industrial", "Machinery"],
    "auction_format": "Hybrid",
    "auction_platform": "Proprietary Online Platform",
    "categories_auctioned": ["Property", "Vehicles", "Industrial Assets"],
    "auction_frequency": "Weekly",
    "collection_locations": ["Pretoria"],
    "provincial_reach": ["Gauteng"],
    "national_or_regional": "National",
    "best_for_tags": ["Dealers", "Property Investors"],
    "operational_metrics": {
      "avg_transfer_days": "7-14",
      "avg_refund_time": "3-5",
      "settlement_flexibility": "Yes",
      "deposit_percent": null,
      "deposit_amount": "R5,000",
      "buyer_premium_percent": "10%",
      "admin_fees": "Variable",
      "vat_on_premium": "Yes",
      "storage_penalties": "Yes",
      "hidden_fees": "No",
      "payment_window_days": "2-3",
      "inspection_offered": "Yes",
      "clearance_rate": "Moderate",
      "discount_competitiveness": "Moderate"
    },
    "reputation_signals": {
      "google_rating": 4.3,
      "google_review_count": 90,
      "trustpilot_rating": null,
      "trustpilot_review_count": null,
      "media_mentions_count": null,
      "media_mentions_sample": [],
      "domain_age_years": 8,
      "social_media_followers": ["Facebook 7k"]
    },
    "complaints_incidents": {
      "deposit_refund": "Yes",
      "transfer_delay": null,
      "misrepresentation": null,
      "dispute_ratio": null,
      "right_of_reply": "Yes"
    },
    "intelligence_fields": {
      "trust_score": null,
      "risk_score": null,
      "fee_transparency_score": null,
      "institutional_grade": null,
      "complaint_rate": null,
      "verification_level": "Unverified"
    }
  },
  {
    "id": 7,
    "auction_house_name": "Claremart Auctioneers",
    "legal_name": "Claremart Auctioneers (Pty) Ltd",
    "website_url": "https://www.claremart.co.za",
    "address": "22 Durban Road",
    "city": "Bellville",
    "province": "Western Cape",
    "contact_email": "info@claremart.co.za",
    "contact_phone": "+27 21 425 8822",
    "years_operating": "40+",
    "company_type": "Pty Ltd",
    "https_secure": "Yes",
    "registration_number": "",
    "vat_registered": "Yes",
    "estate_license": "Yes",
    "popia_policy": "Yes",
    "terms_page": "Yes",
    "refund_policy": "Yes",
    "licensing_claims": "Yes",
    "auction_types": ["Property"],
    "auction_format": "Hybrid",
    "auction_platform": "Proprietary Online Platform",
    "categories_auctioned": ["Residential Property", "Commercial Property"],
    "auction_frequency": "Monthly",
    "collection_locations": ["Bellville"],
    "provincial_reach": ["Western Cape"],
    "national_or_regional": "Regional",
    "best_for_tags": ["Property Investors"],
    "operational_metrics": {
      "avg_transfer_days": "14-21",
      "avg_refund_time": "3-5",
      "settlement_flexibility": "Yes",
      "deposit_percent": "10% of purchase price",
      "deposit_amount": null,
      "buyer_premium_percent": "10%",
      "admin_fees": "Variable",
      "vat_on_premium": "Yes",
      "storage_penalties": "Yes",
      "hidden_fees": "No",
      "payment_window_days": "7",
      "inspection_offered": "Yes",
      "clearance_rate": "High",
      "discount_competitiveness": "Moderate"
    },
    "reputation_signals": {
      "google_rating": 4.1,
      "google_review_count": 50,
      "trustpilot_rating": null,
      "trustpilot_review_count": null,
      "media_mentions_count": null,
      "media_mentions_sample": [],
      "domain_age_years": 20,
      "social_media_followers": ["Facebook 6k"]
    },
    "complaints_incidents": {
      "deposit_refund": null,
      "transfer_delay": "Yes",
      "misrepresentation": null,
      "dispute_ratio": null,
      "right_of_reply": "Yes"
    },
    "intelligence_fields": {
      "trust_score": null,
      "risk_score": null,
      "fee_transparency_score": null,
      "institutional_grade": null,
      "complaint_rate": null,
      "verification_level": "Unverified"
    }
  },
  {
    "id": 8,
    "auction_house_name": "Van's Auctioneers",
    "legal_name": "Van's Auctioneers (Pty) Ltd",
    "website_url": "https://www.vansauctioneers.co.za",
    "address": "76 Koranna Street",
    "city": "Waterkloof",
    "province": "Gauteng",
    "contact_email": "info@vansauctioneers.co.za",
    "contact_phone": "+27 12 343 6394",
    "years_operating": "50+",
    "company_type": "Pty Ltd",
    "https_secure": "Yes",
    "registration_number": "",
    "vat_registered": "Yes",
    "estate_license": "Yes",
    "popia_policy": "Yes",
    "terms_page": "Yes",
    "refund_policy": "Yes",
    "licensing_claims": "Yes",
    "auction_types": ["Property", "Industrial", "Machinery", "Livestock"],
    "auction_format": "Hybrid",
    "auction_platform": "Proprietary Online Platform",
    "categories_auctioned": ["Property", "Industrial", "Livestock"],
    "auction_frequency": "Monthly",
    "collection_locations": ["Pretoria"],
    "provincial_reach": ["Gauteng"],
    "national_or_regional": "Regional",
    "best_for_tags": ["Property Investors", "Industrial Buyers", "Livestock Traders"],
    "operational_metrics": {
      "avg_transfer_days": "14-21",
      "avg_refund_time": "3-5",
      "settlement_flexibility": "Yes",
      "deposit_percent": "10% of purchase price",
      "deposit_amount": null,
      "buyer_premium_percent": "10-12%",
      "admin_fees": "Variable",
      "vat_on_premium": "Yes",
      "storage_penalties": "Yes",
      "hidden_fees": "No",
      "payment_window_days": "7",
      "inspection_offered": "Yes",
      "clearance_rate": "High",
      "discount_competitiveness": "Moderate"
    },
    "reputation_signals": {
      "google_rating": 4.6,
      "google_review_count": 80,
      "trustpilot_rating": null,
      "trustpilot_review_count": null,
      "media_mentions_count": null,
      "media_mentions_sample": [],
      "domain_age_years": 25,
      "social_media_followers": ["Facebook 8k"]
    },
    "complaints_incidents": {
      "deposit_refund": null,
      "transfer_delay": null,
      "misrepresentation": "Yes",
      "dispute_ratio": null,
      "right_of_reply": "Yes"
    },
    "intelligence_fields": {
      "trust_score": null,
      "risk_score": null,
      "fee_transparency_score": null,
      "institutional_grade": null,
      "complaint_rate": null,
      "verification_level": "Unverified"
    }
  },
  {
    "id": 9,
    "auction_house_name": "Park Village Auctions",
    "legal_name": "Park Village Auctions (Pty) Ltd",
    "website_url": "https://www.parkvillage.co.za",
    "address": "Unit 5, Ferndale",
    "city": "Randburg",
    "province": "Gauteng",
    "contact_email": "info@parkvillage.co.za",
    "contact_phone": "+27 11 789 4375",
    "years_operating": "40+",
    "company_type": "Pty Ltd",
    "https_secure": "Yes",
    "registration_number": "",
    "vat_registered": "Yes",
    "estate_license": "Yes",
    "popia_policy": "Yes",
    "terms_page": "Yes",
    "refund_policy": "Yes",
    "licensing_claims": "Yes",
    "auction_types": ["Vehicle", "Property", "Industrial", "Liquidation"],
    "auction_format": "Hybrid",
    "auction_platform": "Proprietary Online Platform",
    "categories_auctioned": ["Property", "Vehicles", "Industrial Assets"],
    "auction_frequency": "Weekly",
    "collection_locations": ["Randburg"],
    "provincial_reach": ["Gauteng"],
    "national_or_regional": "National",
    "best_for_tags": ["Dealers", "Property Investors"],
    "operational_metrics": {
      "avg_transfer_days": "7-14",
      "avg_refund_time": "3-5",
      "settlement_flexibility": "Yes",
      "deposit_percent": null,
      "deposit_amount": "R5,000-R10,000",
      "buyer_premium_percent": "10-15%",
      "admin_fees": "Variable",
      "vat_on_premium": "Yes",
      "storage_penalties": "Yes",
      "hidden_fees": "No",
      "payment_window_days": "2-3",
      "inspection_offered": "Yes",
      "clearance_rate": "Moderate",
      "discount_competitiveness": "Moderate"
    },
    "reputation_signals": {
      "google_rating": 4,
      "google_review_count": 150,
      "trustpilot_rating": null,
      "trustpilot_review_count": null,
      "media_mentions_count": null,
      "media_mentions_sample": [],
      "domain_age_years": 20,
      "social_media_followers": ["Facebook 12k", "LinkedIn 4k"]
    },
    "complaints_incidents": {
      "deposit_refund": "Yes",
      "transfer_delay": "Yes",
      "misrepresentation": null,
      "dispute_ratio": null,
      "right_of_reply": "Yes"
    },
    "intelligence_fields": {
      "trust_score": null,
      "risk_score": null,
      "fee_transparency_score": null,
      "institutional_grade": null,
      "complaint_rate": null,
      "verification_level": "Unverified"
    }
  },
  {
    "id": 10,
    "auction_house_name": "WH Auctioneers",
    "legal_name": "WH Auctioneers (Pty) Ltd",
    "website_url": "https://www.whauctions.com",
    "address": "18 Lakeview Crescent",
    "city": "East Rand",
    "province": "Gauteng",
    "contact_email": "info@whauctions.com",
    "contact_phone": "+27 11 574 5700",
    "years_operating": "20+",
    "company_type": "Pty Ltd",
    "https_secure": "Yes",
    "registration_number": "",
    "vat_registered": "Yes",
    "estate_license": "Yes",
    "popia_policy": "Yes",
    "terms_page": "Yes",
    "refund_policy": "Yes",
    "licensing_claims": "Yes",
    "auction_types": ["Vehicle", "Industrial", "Machinery", "Salvage"],
    "auction_format": "Hybrid",
    "auction_platform": "Proprietary Online Platform",
    "categories_auctioned": ["Vehicles", "Industrial Assets", "Salvage"],
    "auction_frequency": "Weekly",
    "collection_locations": ["East Rand"],
    "provincial_reach": ["Gauteng"],
    "national_or_regional": "National",
    "best_for_tags": ["Dealers", "Salvage Flippers", "Industrial Buyers"],
    "operational_metrics": {
      "avg_transfer_days": "7-10",
      "avg_refund_time": "3-5",
      "settlement_flexibility": "Yes",
      "deposit_percent": null,
      "deposit_amount": "R5,000-R10,000",
      "buyer_premium_percent": "10-12%",
      "admin_fees": "Variable",
      "vat_on_premium": "Yes",
      "storage_penalties": "Yes",
      "hidden_fees": "No",
      "payment_window_days": "2",
      "inspection_offered": "Yes",
      "clearance_rate": "Moderate",
      "discount_competitiveness": "Moderate"
    },
    "reputation_signals": {
      "google_rating": 4.2,
      "google_review_count": 100,
      "trustpilot_rating": null,
      "trustpilot_review_count": null,
      "media_mentions_count": null,
      "media_mentions_sample": [],
      "domain_age_years": 15,
      "social_media_followers": ["Facebook 9k", "LinkedIn 3k"]
    },
    "complaints_incidents": {
      "deposit_refund": null,
      "transfer_delay": null,
      "misrepresentation": "Yes",
      "dispute_ratio": null,
      "right_of_reply": "Yes"
    },
    "intelligence_fields": {
      "trust_score": null,
      "risk_score": null,
      "fee_transparency_score": null,
      "institutional_grade": null,
      "complaint_rate": null,
      "verification_level": "Unverified"
    }
  },
  {
    "id": 11,
    "auction_house_name": "Auction Operation",
    "legal_name": "Auction Operation (Pty) Ltd",
    "website_url": "https://www.auctionoperation.co.za",
    "address": "Johannesburg",
    "city": "Johannesburg",
    "province": "Gauteng",
    "contact_email": "info@auctionoperation.co.za",
    "contact_phone": "+27 87 135 5700",
    "years_operating": "20+",
    "company_type": "Pty Ltd",
    "https_secure": "Yes",
    "registration_number": "",
    "vat_registered": "Yes",
    "estate_license": "Yes",
    "popia_policy": "Yes",
    "terms_page": "Yes",
    "refund_policy": "Yes",
    "licensing_claims": "Yes",
    "auction_types": ["Vehicle", "Furniture", "Equipment", "Property"],
    "auction_format": "Hybrid",
    "auction_platform": "Proprietary Online Platform",
    "categories_auctioned": ["Vehicles", "Property", "Furniture"],
    "auction_frequency": "Weekly",
    "collection_locations": ["Johannesburg"],
    "provincial_reach": ["Gauteng"],
    "national_or_regional": "Regional",
    "best_for_tags": ["Dealers", "First-time buyers"],
    "operational_metrics": {
      "avg_transfer_days": "7-10",
      "avg_refund_time": "3-5",
      "settlement_flexibility": "Yes",
      "deposit_percent": null,
      "deposit_amount": "R5,000",
      "buyer_premium_percent": "10%",
      "admin_fees": "Variable",
      "vat_on_premium": "Yes",
      "storage_penalties": "Yes",
      "hidden_fees": "No",
      "payment_window_days": "2",
      "inspection_offered": "Yes",
      "clearance_rate": "Moderate",
      "discount_competitiveness": "Moderate"
    },
    "reputation_signals": {
      "google_rating": 3.8,
      "google_review_count": 150,
      "trustpilot_rating": null,
      "trustpilot_review_count": null,
      "media_mentions_count": null,
      "media_mentions_sample": [],
      "domain_age_years": 15,
      "social_media_followers": ["Facebook 10k"]
    },
    "complaints_incidents": {
      "deposit_refund": "Yes",
      "transfer_delay": null,
      "misrepresentation": null,
      "dispute_ratio": null,
      "right_of_reply": "Yes"
    },
    "intelligence_fields": {
      "trust_score": null,
      "risk_score": null,
      "fee_transparency_score": null,
      "institutional_grade": null,
      "complaint_rate": null,
      "verification_level": "Unverified"
    }
  },
  {
    "id": 12,
    "auction_house_name": "GoBid",
    "legal_name": "GoBid (Pty) Ltd",
    "website_url": "https://www.gobid.co.za",
    "address": "Online Nationwide",
    "city": "",
    "province": "",
    "contact_email": "info@gobid.co.za",
    "contact_phone": "+27 87 095 0000",
    "years_operating": "5+",
    "company_type": "Pty Ltd",
    "https_secure": "Yes",
    "registration_number": "",
    "vat_registered": "Yes",
    "estate_license": "",
    "popia_policy": "Yes",
    "terms_page": "Yes",
    "refund_policy": "Yes",
    "licensing_claims": "Yes",
    "auction_types": ["Vehicle", "Salvage"],
    "auction_format": "Online",
    "auction_platform": "Proprietary Online Platform",
    "categories_auctioned": ["Vehicles", "Salvage Assets"],
    "auction_frequency": "Weekly",
    "collection_locations": ["National Depots"],
    "provincial_reach": ["National"],
    "national_or_regional": "National",
    "best_for_tags": ["Dealers", "Salvage Flippers"],
    "operational_metrics": {
      "avg_transfer_days": "7",
      "avg_refund_time": "3-5",
      "settlement_flexibility": "Yes",
      "deposit_percent": null,
      "deposit_amount": "R1,000",
      "buyer_premium_percent": "15%",
      "admin_fees": "Variable",
      "vat_on_premium": "Yes",
      "storage_penalties": "Yes",
      "hidden_fees": "No",
      "payment_window_days": "7",
      "inspection_offered": "Yes",
      "clearance_rate": "Moderate",
      "discount_competitiveness": "Moderate"
    },
    "reputation_signals": {
      "google_rating": 4,
      "google_review_count": 80,
      "trustpilot_rating": null,
      "trustpilot_review_count": null,
      "media_mentions_count": null,
      "media_mentions_sample": [],
      "domain_age_years": 5,
      "social_media_followers": ["Facebook 4k"]
    },
    "complaints_incidents": {
      "deposit_refund": null,
      "transfer_delay": null,
      "misrepresentation": "Yes",
      "dispute_ratio": null,
      "right_of_reply": "Yes"
    },
    "intelligence_fields": {
      "trust_score": null,
      "risk_score": null,
      "fee_transparency_score": null,
      "institutional_grade": null,
      "complaint_rate": null,
      "verification_level": "Unverified"
    }
  },
  {
    "id": 13,
    "auction_house_name": "Johannesburg Auctioneers",
    "legal_name": "Johannesburg Auctioneers CC",
    "website_url": "https://www.jhbauctioneers.co.za",
    "address": "Johannesburg",
    "city": "Johannesburg",
    "province": "Gauteng",
    "contact_email": "info@jhbauctioneers.co.za",
    "contact_phone": "+27 60 681 8055",
    "years_operating": "30+",
    "company_type": "CC",
    "https_secure": "Yes",
    "registration_number": "",
    "vat_registered": "Yes",
    "estate_license": "Yes",
    "popia_policy": "Yes",
    "terms_page": "Yes",
    "refund_policy": "Yes",
    "licensing_claims": "Yes",
    "auction_types": ["General", "Estate", "Assets"],
    "auction_format": "Hybrid",
    "auction_platform": "Proprietary Online Platform",
    "categories_auctioned": ["General Assets", "Property"],
    "auction_frequency": "Monthly",
    "collection_locations": ["Johannesburg"],
    "provincial_reach": ["Gauteng"],
    "national_or_regional": "Regional",
    "best_for_tags": ["Dealers", "Estate Buyers"],
    "operational_metrics": {
      "avg_transfer_days": "7",
      "avg_refund_time": "3-5",
      "settlement_flexibility": "Yes",
      "deposit_percent": null,
      "deposit_amount": "R1,000",
      "buyer_premium_percent": "15%",
      "admin_fees": "Variable",
      "vat_on_premium": "Yes",
      "storage_penalties": "Yes",
      "hidden_fees": "No",
      "payment_window_days": "7",
      "inspection_offered": "Yes",
      "clearance_rate": "Moderate",
      "discount_competitiveness": "Moderate"
    },
    "reputation_signals": {
      "google_rating": 4.1,
      "google_review_count": 60,
      "trustpilot_rating": null,
      "trustpilot_review_count": null,
      "media_mentions_count": null,
      "media_mentions_sample": [],
      "domain_age_years": 12,
      "social_media_followers": ["Facebook 3k"]
    },
    "complaints_incidents": {
      "deposit_refund": null,
      "transfer_delay": "Yes",
      "misrepresentation": null,
      "dispute_ratio": null,
      "right_of_reply": "Yes"
    },
    "intelligence_fields": {
      "trust_score": null,
      "risk_score": null,
      "fee_transparency_score": null,
      "institutional_grade": null,
      "complaint_rate": null,
      "verification_level": "Unverified"
    }
  },
  {
    "id": 14,
    "auction_house_name": "SA Group",
    "legal_name": "SA Group (Pty) Ltd",
    "website_url": "https://www.sagroup.co.za",
    "address": "Plot 59, Rietfontein",
    "city": "Pretoria",
    "province": "Gauteng",
    "contact_email": "info@sagroup.co.za",
    "contact_phone": "+27 12 940 8683",
    "years_operating": "15+",
    "company_type": "Pty Ltd",
    "https_secure": "Yes",
    "registration_number": "",
    "vat_registered": "Yes",
    "estate_license": "Yes",
    "popia_policy": "Yes",
    "terms_page": "Yes",
    "refund_policy": "Yes",
    "licensing_claims": "Yes",
    "auction_types": ["Property", "Industrial", "Machinery", "Vehicles"],
    "auction_format": "Hybrid",
    "auction_platform": "Proprietary Online Platform",
    "categories_auctioned": ["Property", "Vehicles", "Industrial Assets"],
    "auction_frequency": "Weekly",
    "collection_locations": ["Pretoria"],
    "provincial_reach": ["Gauteng"],
    "national_or_regional": "National",
    "best_for_tags": ["Dealers", "Property Investors", "Industrial Buyers"],
    "operational_metrics": {
      "avg_transfer_days": "7-14",
      "avg_refund_time": "3-5",
      "settlement_flexibility": "Yes",
      "deposit_percent": null,
      "buyer_premium_percent": "10%",
      "admin_fees": "Variable",
      "vat_on_premium": "Yes",
      "storage_penalties": "Yes",
      "hidden_fees": "No",
      "payment_window_days": "2-3",
      "inspection_offered": "Yes",
      "clearance_rate": "Moderate",
      "discount_competitiveness": "Moderate"
    },
    "reputation_signals": {
      "google_rating": 4,
      "google_review_count": 70,
      "trustpilot_rating": null,
      "trustpilot_review_count": null,
      "media_mentions_count": null,
      "media_mentions_sample": [],
      "domain_age_years": 12,
      "social_media_followers": ["Facebook 5k"]
    },
    "complaints_incidents": {
      "deposit_refund": "Yes",
      "transfer_delay": "Yes",
      "misrepresentation": null,
      "dispute_ratio": null,
      "right_of_reply": "Yes"
    },
    "intelligence_fields": {
      "trust_score": null,
      "risk_score": null,
      "fee_transparency_score": null,
      "institutional_grade": null,
      "complaint_rate": null,
      "verification_level": "Unverified"
    }
  },
  {
    "id": 15,
    "auction_house_name": "Old Johannesburg Warehouse Auctioneers",
    "legal_name": "Old Johannesburg Warehouse Auctioneers (Pty) Ltd",
    "website_url": "https://www.oldjwauctioneers.com",
    "address": "29 Village Road",
    "city": "Johannesburg",
    "province": "Gauteng",
    "contact_email": "info@oldjwauctioneers.com",
    "contact_phone": "+27 11 836 1650",
    "years_operating": "10+",
    "company_type": "Pty Ltd",
    "https_secure": "Yes",
    "registration_number": "",
    "vat_registered": "Yes",
    "estate_license": "Yes",
    "popia_policy": "Yes",
    "terms_page": "Yes",
    "refund_policy": "Yes",
    "licensing_claims": "Yes",
    "auction_types": ["Antiques", "Cars", "Collectibles"],
    "auction_format": "Hybrid",
    "auction_platform": "Proprietary Online Platform",
    "categories_auctioned": ["Antiques", "Cars", "Collectibles"],
    "auction_frequency": "Monthly",
    "collection_locations": ["Johannesburg"],
    "provincial_reach": ["Gauteng"],
    "national_or_regional": "Regional",
    "best_for_tags": ["Collectors", "Dealers"],
    "operational_metrics": {
      "avg_transfer_days": null,
      "avg_refund_time": null,
      "settlement_flexibility": null,
      "deposit_percent": null,
      "deposit_amount": null,
      "buyer_premium_percent": null,
      "admin_fees": null,
      "vat_on_premium": null,
      "storage_penalties": null,
      "hidden_fees": null,
      "payment_window_days": null,
      "inspection_offered": null,
      "clearance_rate": null,
      "discount_competitiveness": null
    },
    "reputation_signals": {
      "google_rating": 4.5,
      "google_review_count": 120,
      "trustpilot_rating": null,
      "trustpilot_review_count": null,
      "media_mentions_count": null,
      "media_mentions_sample": [],
      "domain_age_years": 8,
      "social_media_followers": ["Facebook 7k", "Instagram 5k"]
    },
    "complaints_incidents": {
      "deposit_refund": null,
      "transfer_delay": null,
      "misrepresentation": "Yes",
      "dispute_ratio": null,
      "right_of_reply": "Yes"
    },
    "intelligence_fields": {
      "trust_score": null,
      "risk_score": null,
      "fee_transparency_score": null,
      "institutional_grade": null,
      "complaint_rate": null,
      "verification_level": "Unverified"
    }
  },
  {
    "id": 16,
    "auction_house_name": "Marietjie Keet Auctioneers",
    "legal_name": "Marietjie Keet Auctioneers CC",
    "website_url": "https://www.mkauctioneers.co.za",
    "address": "Pretoria",
    "city": "Pretoria",
    "province": "Gauteng",
    "contact_email": "info@mkauctioneers.co.za",
    "contact_phone": "+27 12 343 6394",
    "years_operating": "20+",
    "company_type": "CC",
    "https_secure": "Yes",
    "registration_number": "",
    "vat_registered": "Yes",
    "estate_license": "Yes",
    "popia_policy": "Yes",
    "terms_page": "Yes",
    "refund_policy": "Yes",
    "licensing_claims": "Yes",
    "auction_types": ["General", "Property"],
    "auction_format": "Hybrid",
    "auction_platform": "Proprietary Online Platform",
    "categories_auctioned": ["Property", "General Assets"],
    "auction_frequency": "Monthly",
    "collection_locations": ["Pretoria"],
    "provincial_reach": ["Gauteng"],
    "national_or_regional": "Regional",
    "best_for_tags": ["Property Investors"],
    "operational_metrics": {
      "avg_transfer_days": "14",
      "avg_refund_time": "3-5",
      "settlement_flexibility": "Yes",
      "deposit_percent": "10% of purchase price",
      "deposit_amount": null,
      "buyer_premium_percent": "10-12%",
      "admin_fees": "Variable",
      "vat_on_premium": "Yes",
      "storage_penalties": "Yes",
      "hidden_fees": "No",
      "payment_window_days": "7",
      "inspection_offered": "Yes",
      "clearance_rate": "Moderate",
      "discount_competitiveness": "Moderate"
    },
    "reputation_signals": {
      "google_rating": 4,
      "google_review_count": 25,
      "trustpilot_rating": null,
      "trustpilot_review_count": null,
      "media_mentions_count": null,
      "media_mentions_sample": [],
      "domain_age_years": 10,
      "social_media_followers": ["Facebook 2k"]
    },
    "complaints_incidents": {
      "deposit_refund": "Yes",
      "transfer_delay": null,
      "misrepresentation": null,
      "dispute_ratio": null,
      "right_of_reply": "Yes"
    },
    "intelligence_fields": {
      "trust_score": null,
      "risk_score": null,
      "fee_transparency_score": null,
      "institutional_grade": null,
      "complaint_rate": null,
      "verification_level": "Unverified"
    }
  },
  {
    "id": 17,
    "auction_house_name": "Cahi Auctioneers",
    "legal_name": "Cahi Auctioneers (Pty) Ltd",
    "website_url": "https://www.cahi.co.za",
    "address": "Tyger Valley",
    "city": "Tyger Valley",
    "province": "Western Cape",
    "contact_email": "info@cahi.co.za",
    "contact_phone": "+27 21 975 7222",
    "years_operating": "15+",
    "company_type": "Pty Ltd",
    "https_secure": "Yes",
    "registration_number": "",
    "vat_registered": "Yes",
    "estate_license": "Yes",
    "popia_policy": "Yes",
    "terms_page": "Yes",
    "refund_policy": "Yes",
    "licensing_claims": "Yes",
    "auction_types": ["General", "Property"],
    "auction_format": "Hybrid",
    "auction_platform": "Proprietary Online Platform",
    "categories_auctioned": ["Property", "General Assets"],
    "auction_frequency": "Monthly",
    "collection_locations": ["Tyger Valley"],
    "provincial_reach": ["Western Cape"],
    "national_or_regional": "Regional",
    "best_for_tags": ["Property Investors"],
    "operational_metrics": {
      "avg_transfer_days": "14",
      "avg_refund_time": "3-5",
      "settlement_flexibility": "Yes",
      "deposit_percent": "10% of purchase price",
      "deposit_amount": null,
      "buyer_premium_percent": "10%",
      "admin_fees": "Variable",
      "vat_on_premium": "Yes",
      "storage_penalties": "Yes",
      "hidden_fees": "No",
      "payment_window_days": "7",
      "inspection_offered": "Yes",
      "clearance_rate": "Moderate",
      "discount_competitiveness": "Moderate"
    },
    "reputation_signals": {
      "google_rating": 4.1,
      "google_review_count": 30,
      "trustpilot_rating": null,
      "trustpilot_review_count": null,
      "media_mentions_count": null,
      "media_mentions_sample": [],
      "domain_age_years": 12,
      "social_media_followers": ["Facebook 1.5k"]
    },
    "complaints_incidents": {
      "deposit_refund": null,
      "transfer_delay": "Yes",
      "misrepresentation": null,
      "dispute_ratio": null,
      "right_of_reply": "Yes"
    },
    "intelligence_fields": {
      "trust_score": null,
      "risk_score": null,
      "fee_transparency_score": null,
      "institutional_grade": null,
      "complaint_rate": null,
      "verification_level": "Unverified"
    }
  },
  {
    "id": 18,
    "auction_house_name": "Strauss & Co Fine Art Auctioneers",
    "legal_name": "Strauss & Co (Pty) Ltd",
    "website_url": "https://www.straussart.co.za",
    "address": "19th Floor, The Marble Towers",
    "city": "Johannesburg",
    "province": "Gauteng",
    "contact_email": "info@straussart.co.za",
    "contact_phone": "+27 11 728 8246",
    "years_operating": "15+",
    "company_type": "Pty Ltd",
    "https_secure": "Yes",
    "registration_number": "",
    "vat_registered": "Yes",
    "estate_license": "",
    "popia_policy": "Yes",
    "terms_page": "Yes",
    "refund_policy": "Yes",
    "licensing_claims": "Yes",
    "auction_types": ["Fine Art", "Collectibles", "Wine"],
    "auction_format": "Hybrid",
    "auction_platform": "Proprietary Online Platform",
    "categories_auctioned": ["Fine Art", "Collectibles", "Wine"],
    "auction_frequency": "Quarterly",
    "collection_locations": ["Johannesburg", "Cape Town"],
    "provincial_reach": ["Gauteng", "Western Cape"],
    "national_or_regional": "National",
    "best_for_tags": ["Art Collectors", "Wine Enthusiasts", "High-net-worth Buyers"],
    "operational_metrics": {
      "avg_transfer_days": "21",
      "avg_refund_time": "5-7",
      "settlement_flexibility": "Yes",
      "deposit_percent": "10% of purchase price",
      "deposit_amount": null,
      "buyer_premium_percent": "15%",
      "admin_fees": "Variable",
      "vat_on_premium": "Yes",
      "storage_penalties": "Yes",
      "hidden_fees": "No",
      "payment_window_days": "7",
      "inspection_offered": "Yes",
      "clearance_rate": "High",
      "discount_competitiveness": "Low"
    },
    "reputation_signals": {
      "google_rating": 4.7,
      "google_review_count": 200,
      "trustpilot_rating": null,
      "trustpilot_review_count": null,
      "media_mentions_count": 50,
      "media_mentions_sample": ["Business Day", "Financial Mail", "Art Times"],
      "domain_age_years": 15,
      "social_media_followers": ["Facebook 20k", "Instagram 15k", "LinkedIn 5k"]
    },
    "complaints_incidents": {
      "deposit_refund": null,
      "transfer_delay": null,
      "misrepresentation": null,
      "dispute_ratio": "Low",
      "right_of_reply": "Yes"
    },
    "intelligence_fields": {
      "trust_score": "High",
      "risk_score": "Low",
      "fee_transparency_score": "High",
      "institutional_grade": "A",
      "complaint_rate": "Low",
      "verification_level": "Verified"
    }
  },
  {
    "id": 19,
    "auction_house_name": "Nuco Auctioneers",
    "legal_name": "Nuco Auctioneers (Pty) Ltd",
    "website_url": "https://www.nucoauctioneers.co.za",
    "address": "Plot 59, Rietfontein",
    "city": "Centurion",
    "province": "Gauteng",
    "contact_email": "info@nucoauctioneers.co.za",
    "contact_phone": "+27 12 940 8683",
    "years_operating": "20+",
    "company_type": "Pty Ltd",
    "https_secure": "Yes",
    "registration_number": "",
    "vat_registered": "Yes",
    "estate_license": "Yes",
    "popia_policy": "Yes",
    "terms_page": "Yes",
    "refund_policy": "Yes",
    "licensing_claims": "Yes",
    "auction_types": ["Vehicle", "Industrial", "Machinery"],
    "auction_format": "Hybrid",
    "auction_platform": "Proprietary Online Platform",
    "categories_auctioned": ["Vehicles", "Industrial Assets"],
    "auction_frequency": "Weekly",
    "collection_locations": ["Centurion"],
    "provincial_reach": ["Gauteng"],
    "national_or_regional": "Regional",
    "best_for_tags": ["Dealers", "Industrial Buyers"],
    "operational_metrics": {
      "avg_transfer_days": "7-10",
      "avg_refund_time": "3-5",
      "settlement_flexibility": "Yes",
      "deposit_percent": null,
      "deposit_amount": "R5,000-R10,000",
      "buyer_premium_percent": "10-12%",
      "admin_fees": "Variable",
      "vat_on_premium": "Yes",
      "storage_penalties": "Yes",
      "hidden_fees": "No",
      "payment_window_days": "2-3",
      "inspection_offered": "Yes",
      "clearance_rate": "Moderate",
      "discount_competitiveness": "Moderate"
    },
    "reputation_signals": {
      "google_rating": 4.3,
      "google_review_count": 90,
      "trustpilot_rating": null,
      "trustpilot_review_count": null,
      "media_mentions_count": null,
      "media_mentions_sample": [],
      "domain_age_years": 10,
      "social_media_followers": ["Facebook 6k"]
    },
    "complaints_incidents": {
      "deposit_refund": "Yes",
      "transfer_delay": null,
      "misrepresentation": null,
      "dispute_ratio": null,
      "right_of_reply": "Yes"
    },
    "intelligence_fields": {
      "trust_score": null,
      "risk_score": null,
      "fee_transparency_score": null,
      "institutional_grade": null,
      "complaint_rate": null,
      "verification_level": "Unverified"
    }
  },
  {
    "id": 20,
    "auction_house_name": "Grand Oak Auctions",
    "legal_name": "Grand Oak Auctions (Pty) Ltd",
    "website_url": "https://www.grandoak.co.za",
    "address": "Johannesburg",
    "city": "Johannesburg",
    "province": "Gauteng",
    "contact_email": "info@grandoak.co.za",
    "contact_phone": "+27 63 740 1878",
    "years_operating": "10+",
    "company_type": "Pty Ltd",
    "https_secure": "Yes",
    "registration_number": "",
    "vat_registered": "Yes",
    "estate_license": "Yes",
    "popia_policy": "Yes",
    "terms_page": "Yes",
    "refund_policy": "Yes",
    "licensing_claims": "Yes",
    "auction_types": ["Industrial Machinery", "Vehicles", "Property", "Estates", "Collectibles"],
    "auction_format": "Hybrid",
    "auction_platform": "Proprietary Online Platform",
    "categories_auctioned": ["Machinery", "Vehicles", "Property", "Art", "Antiques", "Jewellery", "Furniture", "Decor"],
    "auction_frequency": "Weekly",
    "collection_locations": ["Johannesburg"],
    "provincial_reach": ["Gauteng"],
    "national_or_regional": "Regional",
    "best_for_tags": ["Industrial Buyers", "Estate Executors", "Collectors", "Dealers"],
    "operational_metrics": {
      "avg_transfer_days": "14",
      "avg_refund_time": "3-5",
      "settlement_flexibility": "Yes",
      "deposit_percent": "10% of purchase price",
      "deposit_amount": null,
      "buyer_premium_percent": "10-12%",
      "admin_fees": "Variable",
      "vat_on_premium": "Yes",
      "storage_penalties": "Yes",
      "hidden_fees": "No",
      "payment_window_days": "7",
      "inspection_offered": "Yes",
      "clearance_rate": "Moderate",
      "discount_competitiveness": "Moderate"
    },
    "reputation_signals": {
      "google_rating": null,
      "google_review_count": null,
      "trustpilot_rating": null,
      "trustpilot_review_count": null,
      "media_mentions_count": null,
      "media_mentions_sample": [],
      "domain_age_years": null,
      "social_media_followers": []
    },
    "complaints_incidents": {
      "deposit_refund": null,
      "transfer_delay": null,
      "misrepresentation": null,
      "dispute_ratio": null,
      "right_of_reply": "Yes"
    },
    "intelligence_fields": {
      "trust_score": null,
      "risk_score": null,
      "fee_transparency_score": null,
      "institutional_grade": null,
      "complaint_rate": null,
      "verification_level": "Unverified"
    }
  },
  {
    "id": 21,
    "auction_house_name": "Traveling Auctioneers SA",
    "legal_name": "Traveling Auctioneers SA CC",
    "website_url": "https://www.travelingauctioneers.co.za",
    "address": "24 OR Tambo Road",
    "city": "Emalahleni (Witbank)",
    "province": "Mpumalanga",
    "contact_email": "info@travelingauctioneers.co.za",
    "contact_phone": "+27 66 035 1658",
    "years_operating": "10+",
    "company_type": "CC",
    "https_secure": "Yes",
    "registration_number": "",
    "vat_registered": "Yes",
    "estate_license": "Yes",
    "popia_policy": "Yes",
    "terms_page": "Yes",
    "refund_policy": "Yes",
    "licensing_claims": "Yes",
    "auction_types": ["Antiques", "Collectibles", "Household Goods", "Furniture"],
    "auction_format": "Live On-Site",
    "auction_platform": "Physical Auction House",
    "categories_auctioned": ["Antiques", "Collectibles", "Furniture", "Household Items"],
    "auction_frequency": "Weekly (Saturdays)",
    "collection_locations": ["Emalahleni (Witbank)"],
    "provincial_reach": ["Mpumalanga"],
    "national_or_regional": "Regional",
    "best_for_tags": ["Collectors", "Household Buyers", "First-time Bidders"],
    "operational_metrics": {
      "avg_transfer_days": "7-10",
      "avg_refund_time": "3-5",
      "settlement_flexibility": "Yes",
      "deposit_percent": null,
      "deposit_amount": "R1,000-R5,000",
      "buyer_premium_percent": "10%",
      "admin_fees": "Variable",
      "vat_on_premium": "Yes",
      "storage_penalties": "Yes",
      "hidden_fees": "No",
      "payment_window_days": "2-3",
      "inspection_offered": "Yes",
      "clearance_rate": "Moderate",
      "discount_competitiveness": "High"
    },
    "reputation_signals": {
      "google_rating": null,
      "google_review_count": null,
      "trustpilot_rating": null,
      "trustpilot_review_count": null,
      "media_mentions_count": null,
      "media_mentions_sample": [],
      "domain_age_years": null,
      "social_media_followers": ["Facebook 2k+"]
    },
    "complaints_incidents": {
      "deposit_refund": null,
      "transfer_delay": null,
      "misrepresentation": null,
      "dispute_ratio": null,
      "right_of_reply": "Yes"
    },
    "intelligence_fields": {
      "trust_score": null,
      "risk_score": null,
      "fee_transparency_score": null,
      "institutional_grade": null,
      "complaint_rate": null,
      "verification_level": "Unverified"
    }
  },
  {
    "id": 22,
    "auction_house_name": "Bernardi Auctioneers",
    "legal_name": "Bernardi Auctioneers (Pty) Ltd",
    "website_url": "https://www.bernardiauctioneers.co.za",
    "address": "Bernardi Place, 65 Thomson Street, Colbyn",
    "city": "Pretoria",
    "province": "Gauteng",
    "contact_email": "info@bernardiauctioneers.co.za",
    "contact_phone": "+27 12 430 6914",
    "years_operating": "40+",
    "company_type": "Pty Ltd",
    "https_secure": "Yes",
    "registration_number": "",
    "vat_registered": "Yes",
    "estate_license": "Yes",
    "popia_policy": "Yes",
    "terms_page": "Yes",
    "refund_policy": "Yes",
    "licensing_claims": "Yes",
    "auction_types": ["Fine Art", "Antiques", "Collectibles", "Jewellery", "Africana", "Rare Books", "Numismatics"],
    "auction_format": "Hybrid",
    "auction_platform": "Proprietary Online Platform",
    "categories_auctioned": ["Art", "Antiques", "Collectibles", "Jewellery", "Books", "Maps", "Medals"],
    "auction_frequency": "Monthly (Timed Online & Live)",
    "collection_locations": ["Pretoria"],
    "provincial_reach": ["Gauteng"],
    "national_or_regional": "National",
    "best_for_tags": ["Collectors", "Art Investors", "Book Collectors", "Jewellery Buyers"],
    "operational_metrics": {
      "avg_transfer_days": "14-21",
      "avg_refund_time": "5-7",
      "settlement_flexibility": "Yes",
      "deposit_percent": "10% of purchase price",
      "deposit_amount": null,
      "buyer_premium_percent": "12%",
      "admin_fees": "Variable",
      "vat_on_premium": "Yes",
      "storage_penalties": "Yes",
      "hidden_fees": "No",
      "payment_window_days": "7",
      "inspection_offered": "Yes",
      "clearance_rate": "High",
      "discount_competitiveness": "Moderate"
    },
    "reputation_signals": {
      "google_rating": 4.4,
      "google_review_count": 50,
      "trustpilot_rating": null,
      "trustpilot_review_count": null,
      "media_mentions_count": 10,
      "media_mentions_sample": ["Art.co.za", "MutualArt"],
      "domain_age_years": 20,
      "social_media_followers": ["Facebook 3k"]
    },
    "complaints_incidents": {
      "deposit_refund": null,
      "transfer_delay": null,
      "misrepresentation": null,
      "dispute_ratio": "Low",
      "right_of_reply": "Yes"
    },
    "intelligence_fields": {
      "trust_score": "High",
      "risk_score": "Low",
      "fee_transparency_score": "Moderate",
      "institutional_grade": "B+",
      "complaint_rate": "Low",
      "verification_level": "Verified"
    }
  },
  {
    "id": 23,
    "auction_house_name": "AuctionInc",
    "legal_name": "AuctionInc (Pty) Ltd",
    "website_url": "https://www.auctioninc.co.za",
    "address": "2nd Floor, Katherine & West Building",
    "city": "Sandton",
    "province": "Gauteng",
    "contact_email": "info@auctioninc.co.za",
    "contact_phone": "+27 11 268 0227",
    "years_operating": "10+",
    "company_type": "Pty Ltd",
    "https_secure": "Yes",
    "registration_number": "",
    "vat_registered": "Yes",
    "estate_license": "Yes",
    "popia_policy": "Yes",
    "terms_page": "Yes",
    "refund_policy": "Yes",
    "licensing_claims": "Yes",
    "auction_types": ["Property", "Commercial", "Residential"],
    "auction_format": "Hybrid",
    "auction_platform": "Proprietary Online Platform",
    "categories_auctioned": ["Commercial Property", "Residential Property"],
    "auction_frequency": "Monthly",
    "collection_locations": ["Sandton"],
    "provincial_reach": ["Gauteng"],
    "national_or_regional": "National",
    "best_for_tags": ["Property Investors", "Commercial Developers"],
    "operational_metrics": {
      "avg_transfer_days": "21",
      "avg_refund_time": "5-7",
      "settlement_flexibility": "Yes",
      "deposit_percent": "10%",
      "deposit_amount": null,
      "buyer_premium_percent": "5%",
      "admin_fees": "Variable",
      "vat_on_premium": "Yes",
      "storage_penalties": "Yes",
      "hidden_fees": "No",
      "payment_window_days": "7",
      "inspection_offered": "Yes",
      "clearance_rate": "High",
      "discount_competitiveness": "Moderate"
    },
    "reputation_signals": {
      "google_rating": 4.3,
      "google_review_count": 40,
      "trustpilot_rating": null,
      "trustpilot_review_count": null,
      "media_mentions_count": 5,
      "media_mentions_sample": ["Property24", "BusinessTech"],
      "domain_age_years": 12,
      "social_media_followers": ["Facebook 2k", "LinkedIn 1.5k"]
    },
    "complaints_incidents": {
      "deposit_refund": null,
      "transfer_delay": null,
      "misrepresentation": null,
      "dispute_ratio": "Low",
      "right_of_reply": "Yes"
    },
    "intelligence_fields": {
      "trust_score": "High",
      "risk_score": "Low",
      "fee_transparency_score": "Moderate",
      "institutional_grade": "B+",
      "complaint_rate": "Low",
      "verification_level": "Verified"
    }
  },
  {
    "id": 24,
    "auction_house_name": "Cape Auctioneers",
    "legal_name": "Cape Auctioneers (Pty) Ltd",
    "website_url": "https://www.capeauctioneers.com",
    "address": "37A Stella Cove Montague",
    "city": "Cape Town",
    "province": "Western Cape",
    "contact_email": "info@capeauctioneers.com",
    "contact_phone": "+27 21 982 5466",
    "years_operating": "20+",
    "company_type": "Pty Ltd",
    "https_secure": "Yes",
    "registration_number": "",
    "vat_registered": "Yes",
    "estate_license": "Yes",
    "popia_policy": "Yes",
    "terms_page": "Yes",
    "refund_policy": "Yes",
    "licensing_claims": "Yes",
    "auction_types": ["General", "Property", "Industrial", "Machinery", "Vehicles"],
    "auction_format": "Hybrid",
    "auction_platform": "Proprietary Online Platform",
    "categories_auctioned": ["Property", "Vehicles", "Industrial Assets", "Furniture", "Household Goods"],
    "auction_frequency": "Weekly",
    "collection_locations": ["Cape Town"],
    "provincial_reach": ["Western Cape"],
    "national_or_regional": "Regional",
    "best_for_tags": ["Dealers", "Property Investors", "Household Buyers"],
    "operational_metrics": {
      "avg_transfer_days": "14",
      "avg_refund_time": "3-5",
      "settlement_flexibility": "Yes",
      "deposit_percent": "10% of purchase price",
      "deposit_amount": null,
      "buyer_premium_percent": "10-12%",
      "admin_fees": "Variable",
      "vat_on_premium": "Yes",
      "storage_penalties": "Yes",
      "hidden_fees": "No",
      "payment_window_days": "7",
      "inspection_offered": "Yes",
      "clearance_rate": "Moderate",
      "discount_competitiveness": "High"
    },
    "reputation_signals": {
      "google_rating": 4.2,
      "google_review_count": 60,
      "trustpilot_rating": null,
      "trustpilot_review_count": null,
      "media_mentions_count": 5,
      "media_mentions_sample": ["Cape Times", "Property24"],
      "domain_age_years": 15,
      "social_media_followers": ["Facebook 4k"]
    },
    "complaints_incidents": {
      "deposit_refund": "Yes",
      "transfer_delay": null,
      "misrepresentation": null,
      "dispute_ratio": "Low",
      "right_of_reply": "Yes"
    },
    "intelligence_fields": {
      "trust_score": "Moderate",
      "risk_score": "Low",
      "fee_transparency_score": "Moderate",
      "institutional_grade": "B",
      "complaint_rate": "Low",
      "verification_level": "Unverified"
    }
  },
  {
    "id": 25,
    "auction_house_name": "WCT Auctions",
    "legal_name": "WCT Auctions (Pty) Ltd",
    "website_url": "https://www.wctauctions.co.za",
    "address": "123 Taaifontein st Wolmaranspoort",
    "city": "Pretoria",
    "province": "Gauteng",
    "contact_email": "info@wctauctions.co.za",
    "contact_phone": "+27 82 452 0299",
    "years_operating": "10+",
    "company_type": "Pty Ltd",
    "https_secure": "Yes",
    "registration_number": "",
    "vat_registered": "Yes",
    "estate_license": "Yes",
    "popia_policy": "Yes",
    "terms_page": "Yes",
    "refund_policy": "Yes",
    "licensing_claims": "Yes",
    "auction_types": ["Vehicles", "Property", "Industrial", "Machinery"],
    "auction_format": "Hybrid",
    "auction_platform": "Proprietary Online Platform",
    "categories_auctioned": ["Vehicles", "Property", "Industrial Assets"],
    "auction_frequency": "Weekly",
    "collection_locations": ["Durban"],
    "provincial_reach": ["KwaZulu-Natal"],
    "national_or_regional": "Regional",
    "best_for_tags": ["Dealers", "Property Investors", "Industrial Buyers"],
    "operational_metrics": {
      "avg_transfer_days": "7-14",
      "avg_refund_time": "3-5",
      "settlement_flexibility": "Yes",
      "deposit_percent": null,
      "deposit_amount": "R5,000-R10,000",
      "buyer_premium_percent": "10-12%",
      "admin_fees": "Variable",
      "vat_on_premium": "Yes",
      "storage_penalties": "Yes",
      "hidden_fees": "No",
      "payment_window_days": "2-3",
      "inspection_offered": "Yes",
      "clearance_rate": "Moderate",
      "discount_competitiveness": "Moderate"
    },
    "reputation_signals": {
      "google_rating": 4,
      "google_review_count": 25,
      "trustpilot_rating": null,
      "trustpilot_review_count": null,
      "media_mentions_count": 2,
      "media_mentions_sample": ["Local Durban Press"],
      "domain_age_years": 8,
      "social_media_followers": ["Facebook 1.5k"]
    },
    "complaints_incidents": {
      "deposit_refund": null,
      "transfer_delay": null,
      "misrepresentation": null,
      "dispute_ratio": "Low",
      "right_of_reply": "Yes"
    },
    "intelligence_fields": {
      "trust_score": "Moderate",
      "risk_score": "Low",
      "fee_transparency_score": "Moderate",
      "institutional_grade": "B",
      "complaint_rate": "Low",
      "verification_level": "Unverified"
    }
  },
  {
    "id": 26,
    "auction_house_name": "Ambassador Auctioneers",
    "legal_name": "Ambassador Auctioneers CC",
    "website_url": "https://www.ambassadorauctioneers.co.za",
    "address": "Plot 59, Rietfontein",
    "city": "Pretoria",
    "province": "Gauteng",
    "contact_email": "info@ambassadorauctioneers.co.za",
    "contact_phone": "+27 12 343 6394",
    "years_operating": "30+",
    "company_type": "CC",
    "https_secure": "Yes",
    "registration_number": "",
    "vat_registered": "Yes",
    "estate_license": "Yes",
    "popia_policy": "Yes",
    "terms_page": "Yes",
    "refund_policy": "Yes",
    "licensing_claims": "Yes",
    "auction_types": ["Property", "Vehicles", "General Assets", "Furniture"],
    "auction_format": "Hybrid",
    "auction_platform": "Proprietary Online Platform",
    "categories_auctioned": ["Property", "Vehicles", "Furniture", "General Assets"],
    "auction_frequency": "Weekly",
    "collection_locations": ["Pretoria"],
    "provincial_reach": ["Gauteng"],
    "national_or_regional": "Regional",
    "best_for_tags": ["Dealers", "Property Investors", "Household Buyers"],
    "operational_metrics": {
      "avg_transfer_days": "14",
      "avg_refund_time": "3-5",
      "settlement_flexibility": "Yes",
      "deposit_percent": "10% of purchase price",
      "deposit_amount": null,
      "buyer_premium_percent": "10%",
      "admin_fees": "Variable",
      "vat_on_premium": "Yes",
      "storage_penalties": "Yes",
      "hidden_fees": "No",
      "payment_window_days": "7",
      "inspection_offered": "Yes",
      "clearance_rate": "Moderate",
      "discount_competitiveness": "Moderate"
    },
    "reputation_signals": {
      "google_rating": 4.2,
      "google_review_count": 40,
      "trustpilot_rating": null,
      "trustpilot_review_count": null,
      "media_mentions_count": 3,
      "media_mentions_sample": ["Pretoria News"],
      "domain_age_years": 15,
      "social_media_followers": ["Facebook 2k"]
    },
    "complaints_incidents": {
      "deposit_refund": "Yes",
      "transfer_delay": null,
      "misrepresentation": null,
      "dispute_ratio": "Low",
      "right_of_reply": "Yes"
    },
    "intelligence_fields": {
      "trust_score": "Moderate",
      "risk_score": "Low",
      "fee_transparency_score": "Moderate",
      "institutional_grade": "B",
      "complaint_rate": "Low",
      "verification_level": "Unverified"
    }
  },
  {
    "id": 27,
    "auction_house_name": "Westgate Walding Auctioneers",
    "legal_name": "Westgate Walding Auctioneers CC",
    "website_url": "https://www.westgatewalding.co.za",
    "address": "Krugersdorp",
    "city": "Krugersdorp",
    "province": "Gauteng",
    "contact_email": "info@westgatewalding.co.za",
    "contact_phone": "+27 11 783 7260",
    "years_operating": "20+",
    "company_type": "CC",
    "https_secure": "Yes",
    "registration_number": "",
    "vat_registered": "Yes",
    "estate_license": "Yes",
    "popia_policy": "Yes",
    "terms_page": "Yes",
    "refund_policy": "Yes",
    "licensing_claims": "Yes",
    "auction_types": ["General", "Property", "Vehicles", "Furniture"],
    "auction_format": "Hybrid",
    "auction_platform": "Proprietary Online Platform",
    "categories_auctioned": ["Property", "Vehicles", "Furniture", "General Assets"],
    "auction_frequency": "Weekly",
    "collection_locations": ["Krugersdorp"],
    "provincial_reach": ["Gauteng"],
    "national_or_regional": "Regional",
    "best_for_tags": ["Dealers", "Property Investors", "Household Buyers"],
    "operational_metrics": {
      "avg_transfer_days": "14",
      "avg_refund_time": "3-5",
      "settlement_flexibility": "Yes",
      "deposit_percent": "10% of purchase price",
      "deposit_amount": null,
      "buyer_premium_percent": "10-12%",
      "admin_fees": "Variable",
      "vat_on_premium": "Yes",
      "storage_penalties": "Yes",
      "hidden_fees": "No",
      "payment_window_days": "7",
      "inspection_offered": "Yes",
      "clearance_rate": "Moderate",
      "discount_competitiveness": "Moderate"
    },
    "reputation_signals": {
      "google_rating": 4,
      "google_review_count": 20,
      "trustpilot_rating": null,
      "trustpilot_review_count": null,
      "media_mentions_count": 2,
      "media_mentions_sample": ["Krugersdorp Local Press"],
      "domain_age_years": 10,
      "social_media_followers": ["Facebook 1k"]
    },
    "complaints_incidents": {
      "deposit_refund": null,
      "transfer_delay": null,
      "misrepresentation": null,
      "dispute_ratio": "Low",
      "right_of_reply": "Yes"
    },
    "intelligence_fields": {
      "trust_score": "Moderate",
      "risk_score": "Low",
      "fee_transparency_score": "Moderate",
      "institutional_grade": "B",
      "complaint_rate": "Low",
      "verification_level": "Unverified"
    }
  },
  {
    "id": 28,
    "auction_house_name": "Auction Nation Cape Town",
    "legal_name": "Auction Nation (Pty) Ltd",
    "website_url": "https://www.auctionnation.co.za",
    "address": "Cape Town",
    "city": "Cape Town",
    "province": "Western Cape",
    "contact_email": "info@auctionnation.co.za",
    "contact_phone": "+27 10 100 3099",
    "years_operating": "10+",
    "company_type": "Pty Ltd",
    "https_secure": "Yes",
    "registration_number": "",
    "vat_registered": "Yes",
    "estate_license": "Yes",
    "popia_policy": "Yes",
    "terms_page": "Yes",
    "refund_policy": "Yes",
    "licensing_claims": "Yes",
    "auction_types": ["Vehicle", "Property", "Industrial", "Salvage"],
    "auction_format": "Online",
    "auction_platform": "Proprietary Online Platform",
    "categories_auctioned": ["Property", "Vehicles", "Salvage Assets"],
    "auction_frequency": "Weekly",
    "collection_locations": ["Cape Town"],
    "provincial_reach": ["Western Cape"],
    "national_or_regional": "Regional",
    "best_for_tags": ["Dealers", "Salvage Flippers", "Property Investors"],
    "operational_metrics": {
      "avg_transfer_days": "7-14",
      "avg_refund_time": "3-5",
      "settlement_flexibility": "Yes",
      "deposit_percent": null,
      "deposit_amount": "R5,000-R10,000",
      "buyer_premium_percent": "10-15%",
      "admin_fees": "Variable",
      "vat_on_premium": "Yes",
      "storage_penalties": "Yes",
      "hidden_fees": "Yes",
      "payment_window_days": "7",
      "inspection_offered": "Yes",
      "clearance_rate": "Moderate",
      "discount_competitiveness": "Moderate"
    },
    "reputation_signals": {
      "google_rating": 1,
      "google_review_count": 26,
      "trustpilot_rating": null,
      "trustpilot_review_count": null,
      "media_mentions_count": null,
      "media_mentions_sample": [],
      "domain_age_years": 8,
      "social_media_followers": ["Facebook 5k", "LinkedIn 2k"]
    },
    "complaints_incidents": {
      "deposit_refund": "Yes",
      "transfer_delay": null,
      "misrepresentation": "Yes",
      "dispute_ratio": null,
      "right_of_reply": "Yes"
    },
    "intelligence_fields": {
      "trust_score": "Low",
      "risk_score": "High",
      "fee_transparency_score": "Low",
      "institutional_grade": "C",
      "complaint_rate": "High",
      "verification_level": "Unverified"
    }
  },
  {
    "id": 29,
    "auction_house_name": "Stephan Welz & Co",
    "legal_name": "Stephan Welz & Co (Pty) Ltd",
    "website_url": "https://www.swelco.co.za",
    "address": "Nelson Mandela Square, Sandton",
    "city": "Johannesburg",
    "province": "Gauteng",
    "contact_email": "info@swelco.co.za",
    "contact_phone": "+27 11 880 3125",
    "years_operating": "50+",
    "company_type": "Pty Ltd",
    "https_secure": "Yes",
    "registration_number": "",
    "vat_registered": "Yes",
    "estate_license": "",
    "popia_policy": "Yes",
    "terms_page": "Yes",
    "refund_policy": "Yes",
    "licensing_claims": "Yes",
    "auction_types": ["Fine Art", "Antiques", "Jewellery", "Collectibles", "Wine"],
    "auction_format": "Hybrid",
    "auction_platform": "Proprietary Online Platform",
    "categories_auctioned": ["Fine Art", "Antiques", "Jewellery", "Collectibles", "Wine"],
    "auction_frequency": "Quarterly",
    "collection_locations": ["Johannesburg", "Cape Town"],
    "provincial_reach": ["Gauteng", "Western Cape"],
    "national_or_regional": "National",
    "best_for_tags": ["Art Collectors", "Wine Enthusiasts", "Jewellery Buyers", "High-net-worth Investors"],
    "operational_metrics": {
      "avg_transfer_days": "21",
      "avg_refund_time": "5-7",
      "settlement_flexibility": "Yes",
      "deposit_percent": "10%",
      "deposit_amount": null,
      "buyer_premium_percent": "15%",
      "admin_fees": "Variable",
      "vat_on_premium": "Yes",
      "storage_penalties": "Yes",
      "hidden_fees": "No",
      "payment_window_days": "7",
      "inspection_offered": "Yes",
      "clearance_rate": "High",
      "discount_competitiveness": "Moderate"
    },
    "reputation_signals": {
      "google_rating": 4.6,
      "google_review_count": 150,
      "trustpilot_rating": null,
      "trustpilot_review_count": null,
      "media_mentions_count": 30,
      "media_mentions_sample": ["Business Day", "Art Times", "Financial Mail"],
      "domain_age_years": 20,
      "social_media_followers": ["Facebook 10k", "Instagram 8k", "LinkedIn 3k"]
    },
    "complaints_incidents": {
      "deposit_refund": null,
      "transfer_delay": null,
      "misrepresentation": null,
      "dispute_ratio": "Low",
      "right_of_reply": "Yes"
    },
    "intelligence_fields": {
      "trust_score": "High",
      "risk_score": "Low",
      "fee_transparency_score": "High",
      "institutional_grade": "A",
      "complaint_rate": "Low",
      "verification_level": "Verified"
    }
  },
  {
    "id": 30,
    "auction_house_name": "Aucor Auctioneers Bloemfontein",
    "legal_name": "Aucor Auctioneers (Pty) Ltd",
    "website_url": "https://www.aucor.com",
    "address": "Bloemfontein",
    "city": "Bloemfontein",
    "province": "Free State",
    "contact_email": "info@aucor.com",
    "contact_phone": "+27 51 433 2872",
    "years_operating": "50+",
    "company_type": "Pty Ltd",
    "https_secure": "Yes",
    "registration_number": "",
    "vat_registered": "Yes",
    "estate_license": "Yes",
    "popia_policy": "Yes",
    "terms_page": "Yes",
    "refund_policy": "Yes",
    "licensing_claims": "Yes",
    "auction_types": ["Vehicles", "Property", "Industrial", "Machinery", "Liquidation"],
    "auction_format": "Hybrid",
    "auction_platform": "Proprietary Online Platform",
    "categories_auctioned": ["Property", "Vehicles", "Industrial Assets"],
    "auction_frequency": "Weekly",
    "collection_locations": ["Bloemfontein"],
    "provincial_reach": ["Free State"],
    "national_or_regional": "Regional",
    "best_for_tags": ["Dealers", "Property Investors", "Industrial Buyers"],
    "operational_metrics": {
      "avg_transfer_days": "14-21",
      "avg_refund_time": "3-5",
      "settlement_flexibility": "Yes",
      "deposit_percent": "10% of purchase price",
      "deposit_amount": null,
      "buyer_premium_percent": "10-12%",
      "admin_fees": "Variable",
      "vat_on_premium": "Yes",
      "storage_penalties": "Yes",
      "hidden_fees": "No",
      "payment_window_days": "7",
      "inspection_offered": "Yes",
      "clearance_rate": "High",
      "discount_competitiveness": "Moderate"
    },
    "reputation_signals": {
      "google_rating": 3.9,
      "google_review_count": 450,
      "trustpilot_rating": null,
      "trustpilot_review_count": null,
      "media_mentions_count": 5,
      "media_mentions_sample": ["Bloemfontein Courant"],
      "domain_age_years": 20,
      "social_media_followers": ["Facebook 20k", "LinkedIn 5k"]
    },
    "complaints_incidents": {
      "deposit_refund": "Yes",
      "transfer_delay": "Yes",
      "misrepresentation": null,
      "dispute_ratio": "Moderate",
      "right_of_reply": "Yes"
    },
    "intelligence_fields": {
      "trust_score": "Moderate",
      "risk_score": "Moderate",
      "fee_transparency_score": "Moderate",
      "institutional_grade": "B",
      "complaint_rate": "Moderate",
      "verification_level": "Unverified"
    }
  }
]